nf1/F1_communities.py
nf1/NF1_class.py
nf1/__init__.py
scripts/NF1_evaluate.py
scripts/__init__.py
nf1-0.0.4.dist-info/LICENSE
nf1-0.0.4.dist-info/METADATA
nf1-0.0.4.dist-info/WHEEL
nf1-0.0.4.dist-info/entry_points.txt
nf1-0.0.4.dist-info/top_level.txt
nf1-0.0.4.dist-info/RECORD
